locpix/evaluate/__init__.py
locpix/evaluate/metrics.py
locpix/img_processing/__init__.py
locpix/img_processing/render.py
locpix/img_processing/watershed.py
locpix/img_processing/data_loading/__init__.py
locpix/img_processing/data_loading/dataset.py
locpix/img_processing/data_loading/transforms.py
locpix/img_processing/models/__init__.py
locpix/img_processing/models/unet.py
locpix/img_processing/training/__init__.py
locpix/img_processing/training/loss.py
locpix/img_processing/training/train.py
locpix/preprocessing/__init__.py
locpix/preprocessing/datastruc.py
locpix/preprocessing/functions.py
locpix/scripts/__init__.py
locpix/scripts/development/__init__.py
locpix/scripts/development/clean_up.py
locpix/scripts/development/file_names.py
locpix/scripts/development/licenses.py
locpix/scripts/img_seg/__init__.py
locpix/scripts/img_seg/agg_metrics.py
locpix/scripts/img_seg/cellpose_eval.py
locpix/scripts/img_seg/cellpose_train.py
locpix/scripts/img_seg/classic.py
locpix/scripts/img_seg/ilastik_output.py
locpix/scripts/img_seg/ilastik_prep.py
locpix/scripts/img_seg/img_train_prep.py
locpix/scripts/img_seg/membrane_performance.py
locpix/scripts/img_seg/membrane_performance_method.py
locpix/scripts/img_seg/train_prep.py
locpix/scripts/img_seg/unet_train.py
locpix/scripts/preprocessing/__init__.py
locpix/scripts/preprocessing/annotate.py
locpix/scripts/preprocessing/preprocess.py
locpix/templates/__init__.py
locpix/templates/annotate.yaml
locpix/templates/cellpose.yaml
locpix/templates/cellpose_train.yaml
locpix/templates/classic.yaml
locpix/templates/ilastik_prep.yaml
locpix/templates/membrane_performance.yaml
locpix/templates/preprocess.yaml
locpix/templates/train_prep.yaml
locpix/templates/unet_train.yaml
locpix/templates/visualisation.ipynb
locpix/visualise/__init__.py
locpix/visualise/performance.py
locpix/visualise/vis_img.py
locpix-0.1.0.3.dist-info/LICENSE
locpix-0.1.0.3.dist-info/METADATA
locpix-0.1.0.3.dist-info/WHEEL
locpix-0.1.0.3.dist-info/entry_points.txt
locpix-0.1.0.3.dist-info/top_level.txt
locpix-0.1.0.3.dist-info/RECORD
