Metadata-Version: 2.1
Name: locpix
Version: 0.1.0.3
Summary: Package for analysing SMLM data
Author-email: Oliver Umney <scou@leeds.ac.uk>
Project-URL: Homepage, https://github.com/oubino/locpix
Project-URL: Bug Tracker, https://github.com/oubino/locpix/issues
Classifier: Programming Language :: Python :: 3
Classifier: License :: OSI Approved :: MIT License
Classifier: Operating System :: OS Independent
Requires-Python: >=3.7
License-File: LICENSE
Requires-Dist: polars
Requires-Dist: numpy
Requires-Dist: napari
Requires-Dist: matplotlib
Requires-Dist: imageio-ffmpeg
Requires-Dist: PyQt5
Requires-Dist: pyarrow
Requires-Dist: scikit-learn
Requires-Dist: python-dotenv
Requires-Dist: tifffile
Requires-Dist: pre-commit
Requires-Dist: seaborn
Requires-Dist: wandb
